{"languages": [{"short_name": "ar", "full_name": "العربية", "rtl": true}, {"short_name": "en", "full_name": "English", "rtl": false}], "collections": [{"short_name": "bukhari", "ar": "صحيح البخاري", "en": "Sahih al-Bukhari", "languages": ["ar", "en"]}, {"short_name": "muslim", "ar": "صحيح مسلم", "en": "Sahih Muslim", "languages": ["ar", "en"]}, {"short_name": "nasai", "ar": "سنن النسائي", "en": "Sunan an-Nasa'i", "languages": ["ar", "en"]}, {"short_name": "abudawud", "ar": "سنن أبي داود", "en": "Sunan Abi Dawud", "languages": ["ar", "en"]}, {"short_name": "tirmidhi", "ar": "جامع الترمذي ", "en": "Jami` at-Tirmidhi", "languages": ["ar", "en"]}, {"short_name": "ibn_majah", "ar": "سنن ابن ماجه", "en": "Sunan Ibn Majah", "languages": ["ar", "en"]}, {"short_name": "malik", "ar": " موطأ مالك", "en": "Muwatta Malik", "languages": ["ar", "en"]}, {"short_name": "musnad_ahmad", "ar": "مسند أحمد", "en": "Musnad Ahmad", "languages": ["ar", "en"]}, {"short_name": "riyad_assalihin", "ar": "رياض الصالحين ", "en": "Riyad as-Salihin", "languages": ["ar", "en"]}, {"short_name": "mishkat", "ar": "مشكاة المصابيح", "en": "Mishkat al-Masabih", "languages": ["ar", "en"]}, {"short_name": "aladab_almufrad", "ar": "الأدب المفرد", "en": "Al-Adab Al-Mufrad", "languages": ["ar", "en"]}, {"short_name": "shamail", "ar": "الشمائل المحمدية", "en": "Ash-Shama'il Al-Muhammadiyah", "languages": ["ar", "en"]}, {"short_name": "bulugh_almaram", "ar": "بلوغ المرام", "en": "Bulugh al-Maram", "languages": ["ar", "en"]}, {"short_name": "hisn_almuslim", "ar": "حصن المسلم", "en": "Hisn al-Muslim", "languages": ["ar", "en"]}, {"short_name": "fadail_ayaat_suar", "ar": "الجامع المختصر لفضائل الآيات والسور", "en": "Virtues of the Qur'an's Chapters and Verses", "languages": ["ar", "en"]}]}